aws_ecr/__init__.py
aws_ecr/ecr.py
aws_ecr_boto3-0.0.5.dist-info/METADATA
aws_ecr_boto3-0.0.5.dist-info/WHEEL
aws_ecr_boto3-0.0.5.dist-info/top_level.txt
aws_ecr_boto3-0.0.5.dist-info/RECORD
