Metadata-Version: 2.1
Name: aws_ecr_boto3
Version: 0.0.5
Summary: Create and delete aws ecr repository using python boto3 like terraform 
Author: Rukmal Senavirathne
Classifier: Programming Language :: Python :: 3
Classifier: License :: OSI Approved :: MIT License
Classifier: Operating System :: OS Independent
Requires-Python: >=3.6
Requires-Dist: boto3
